module_coupling_metrics/__init__.py
module_coupling_metrics/__main__.py
module_coupling_metrics/app.py
module_coupling_metrics/metrics.py
module_coupling_metrics/project_structure.py
module_coupling_metrics/reflection.py
module_coupling_metrics-0.0.1.dist-info/LICENSE
module_coupling_metrics-0.0.1.dist-info/METADATA
module_coupling_metrics-0.0.1.dist-info/WHEEL
module_coupling_metrics-0.0.1.dist-info/entry_points.txt
module_coupling_metrics-0.0.1.dist-info/top_level.txt
module_coupling_metrics-0.0.1.dist-info/RECORD
