Metadata-Version: 2.1
Name: module-coupling-metrics
Version: 0.0.1
Summary: Compute module coupling metrics for Python projects.
Home-page: https://github.com/Oaz/module_coupling_metrics
Author: Olivier Azeau
License: AGPL-3.0-or-later
Platform: UNKNOWN
Classifier: Development Status :: 3 - Alpha
Classifier: Intended Audience :: Developers
Classifier: License :: OSI Approved :: GNU Affero General Public License v3 or later (AGPLv3+)
Classifier: Operating System :: OS Independent
Classifier: Programming Language :: Python
Classifier: Topic :: Software Development :: Quality Assurance
Classifier: Topic :: Software Development :: Libraries :: Python Modules
Requires-Python: >=3.6
License-File: LICENSE
Requires-Dist: pydeps
Requires-Dist: pandas
Requires-Dist: seaborn
Requires-Dist: matplotlib
